{
  "max_entropy_bits": 4.0,
  "results": [
    {
      "alpha": 0.0,
      "beta": 0.0,
      "gamma": 0.0,
      "mean_entropy_bits": 3.9302744428229524,
      "gap_bits": 0.06972555717704765,
      "per_species": {
        "phono": 3.9783215812634833,
        "lex": 3.780581376240071,
        "syntax": 3.983843573163778,
        "sem": 3.9783512406244776
      }
    },
    {
      "alpha": 0.0,
      "beta": 0.0,
      "gamma": 1.0,
      "mean_entropy_bits": 3.930323714466688,
      "gap_bits": 0.06967628553331195,
      "per_species": {
        "phono": 3.9785492283059596,
        "lex": 3.780566787270674,
        "syntax": 3.983848115853872,
        "sem": 3.978330726436245
      }
    },
    {
      "alpha": 0.0,
      "beta": 0.0,
      "gamma": 5.0,
      "mean_entropy_bits": 3.930442940869333,
      "gap_bits": 0.06955705913066712,
      "per_species": {
        "phono": 3.9793744486089118,
        "lex": 3.7804753279174528,
        "syntax": 3.9837976489271876,
        "sem": 3.978124338023779
      }
    },
    {
      "alpha": 0.0,
      "beta": 0.1,
      "gamma": 0.0,
      "mean_entropy_bits": 3.9302744428229524,
      "gap_bits": 0.06972555717704765,
      "per_species": {
        "phono": 3.9783215812634833,
        "lex": 3.780581376240071,
        "syntax": 3.983843573163778,
        "sem": 3.9783512406244776
      }
    },
    {
      "alpha": 0.0,
      "beta": 0.1,
      "gamma": 1.0,
      "mean_entropy_bits": 3.930323714466688,
      "gap_bits": 0.06967628553331195,
      "per_species": {
        "phono": 3.9785492283059596,
        "lex": 3.780566787270674,
        "syntax": 3.983848115853872,
        "sem": 3.978330726436245
      }
    },
    {
      "alpha": 0.0,
      "beta": 0.1,
      "gamma": 5.0,
      "mean_entropy_bits": 3.930442940869333,
      "gap_bits": 0.06955705913066712,
      "per_species": {
        "phono": 3.9793744486089118,
        "lex": 3.7804753279174528,
        "syntax": 3.9837976489271876,
        "sem": 3.978124338023779
      }
    },
    {
      "alpha": 0.0,
      "beta": 1.0,
      "gamma": 0.0,
      "mean_entropy_bits": 3.971307751100377,
      "gap_bits": 0.028692248899623074,
      "per_species": {
        "phono": 3.970202910484391,
        "lex": 3.9692682978501406,
        "syntax": 3.966218162021651,
        "sem": 3.9795416340453253
      }
    },
    {
      "alpha": 0.0,
      "beta": 1.0,
      "gamma": 1.0,
      "mean_entropy_bits": 3.9717428466391014,
      "gap_bits": 0.028257153360898624,
      "per_species": {
        "phono": 3.9706804327951986,
        "lex": 3.969654716257504,
        "syntax": 3.9667140996464014,
        "sem": 3.9799221378573004
      }
    },
    {
      "alpha": 0.0,
      "beta": 1.0,
      "gamma": 5.0,
      "mean_entropy_bits": 3.973374974342435,
      "gap_bits": 0.026625025657565082,
      "per_species": {
        "phono": 3.9724340609761604,
        "lex": 3.9711540600430766,
        "syntax": 3.9685653177007185,
        "sem": 3.9813464586497838
      }
    },
    {
      "alpha": 1.0,
      "beta": 0.0,
      "gamma": 0.0,
      "mean_entropy_bits": 3.6803071419761837,
      "gap_bits": 0.3196928580238163,
      "per_species": {
        "phono": 3.6158017752577982,
        "lex": 3.3567823486945896,
        "syntax": 3.867234506536005,
        "sem": 3.881409937416343
      }
    },
    {
      "alpha": 1.0,
      "beta": 0.0,
      "gamma": 1.0,
      "mean_entropy_bits": 3.6808789984411723,
      "gap_bits": 0.3191210015588277,
      "per_species": {
        "phono": 3.6168781943550945,
        "lex": 3.357196247564265,
        "syntax": 3.8679338948373516,
        "sem": 3.8815076570079774
      }
    },
    {
      "alpha": 1.0,
      "beta": 0.0,
      "gamma": 5.0,
      "mean_entropy_bits": 3.683041924150992,
      "gap_bits": 0.31695807584900804,
      "per_species": {
        "phono": 3.621009531773479,
        "lex": 3.358769822638439,
        "syntax": 3.8706134191256933,
        "sem": 3.8817749230663576
      }
    },
    {
      "alpha": 1.0,
      "beta": 0.1,
      "gamma": 0.0,
      "mean_entropy_bits": 3.6803071419761837,
      "gap_bits": 0.3196928580238163,
      "per_species": {
        "phono": 3.6158017752577982,
        "lex": 3.3567823486945896,
        "syntax": 3.867234506536005,
        "sem": 3.881409937416343
      }
    },
    {
      "alpha": 1.0,
      "beta": 0.1,
      "gamma": 1.0,
      "mean_entropy_bits": 3.6808789984411723,
      "gap_bits": 0.3191210015588277,
      "per_species": {
        "phono": 3.6168781943550945,
        "lex": 3.357196247564265,
        "syntax": 3.8679338948373516,
        "sem": 3.8815076570079774
      }
    },
    {
      "alpha": 1.0,
      "beta": 0.1,
      "gamma": 5.0,
      "mean_entropy_bits": 3.683041924150992,
      "gap_bits": 0.31695807584900804,
      "per_species": {
        "phono": 3.621009531773479,
        "lex": 3.358769822638439,
        "syntax": 3.8706134191256933,
        "sem": 3.8817749230663576
      }
    },
    {
      "alpha": 1.0,
      "beta": 1.0,
      "gamma": 0.0,
      "mean_entropy_bits": 3.792666840453467,
      "gap_bits": 0.20733315954653309,
      "per_species": {
        "phono": 3.724320139140903,
        "lex": 3.662612983372739,
        "syntax": 3.821780808806582,
        "sem": 3.9619534304936432
      }
    },
    {
      "alpha": 1.0,
      "beta": 1.0,
      "gamma": 1.0,
      "mean_entropy_bits": 3.7930908969729122,
      "gap_bits": 0.20690910302708776,
      "per_species": {
        "phono": 3.7244937956841664,
        "lex": 3.6628438389045352,
        "syntax": 3.822669713644875,
        "sem": 3.962356239658072
      }
    },
    {
      "alpha": 1.0,
      "beta": 1.0,
      "gamma": 5.0,
      "mean_entropy_bits": 3.794730871924277,
      "gap_bits": 0.20526912807572284,
      "per_species": {
        "phono": 3.725146680656796,
        "lex": 3.6637178990031414,
        "syntax": 3.826151417136712,
        "sem": 3.9639074909004597
      }
    },
    {
      "alpha": 5.0,
      "beta": 0.0,
      "gamma": 0.0,
      "mean_entropy_bits": 3.0202514388811394,
      "gap_bits": 0.9797485611188606,
      "per_species": {
        "phono": 3.043417837378983,
        "lex": 2.8918315106855688,
        "syntax": 2.8203575831144065,
        "sem": 3.3253988243455987
      }
    },
    {
      "alpha": 5.0,
      "beta": 0.0,
      "gamma": 1.0,
      "mean_entropy_bits": 3.0199825480494162,
      "gap_bits": 0.9800174519505838,
      "per_species": {
        "phono": 3.043591004619291,
        "lex": 2.8915719706600673,
        "syntax": 2.820520336299623,
        "sem": 3.324246880618685
      }
    },
    {
      "alpha": 5.0,
      "beta": 0.0,
      "gamma": 5.0,
      "mean_entropy_bits": 3.019885857852343,
      "gap_bits": 0.9801141421476571,
      "per_species": {
        "phono": 3.044267172820983,
        "lex": 2.8905286414699005,
        "syntax": 2.8211407218505054,
        "sem": 3.323606895267984
      }
    },
    {
      "alpha": 5.0,
      "beta": 0.1,
      "gamma": 0.0,
      "mean_entropy_bits": 3.0202514388811394,
      "gap_bits": 0.9797485611188606,
      "per_species": {
        "phono": 3.043417837378983,
        "lex": 2.8918315106855688,
        "syntax": 2.8203575831144065,
        "sem": 3.3253988243455987
      }
    },
    {
      "alpha": 5.0,
      "beta": 0.1,
      "gamma": 1.0,
      "mean_entropy_bits": 3.0199825480494162,
      "gap_bits": 0.9800174519505838,
      "per_species": {
        "phono": 3.043591004619291,
        "lex": 2.8915719706600673,
        "syntax": 2.820520336299623,
        "sem": 3.324246880618685
      }
    },
    {
      "alpha": 5.0,
      "beta": 0.1,
      "gamma": 5.0,
      "mean_entropy_bits": 3.019885857852343,
      "gap_bits": 0.9801141421476571,
      "per_species": {
        "phono": 3.044267172820983,
        "lex": 2.8905286414699005,
        "syntax": 2.8211407218505054,
        "sem": 3.323606895267984
      }
    },
    {
      "alpha": 5.0,
      "beta": 1.0,
      "gamma": 0.0,
      "mean_entropy_bits": 2.601568164159256,
      "gap_bits": 1.3984318358407442,
      "per_species": {
        "phono": 2.3310650175471666,
        "lex": 2.247708431345014,
        "syntax": 2.846596204154217,
        "sem": 2.980903003590626
      }
    },
    {
      "alpha": 5.0,
      "beta": 1.0,
      "gamma": 1.0,
      "mean_entropy_bits": 2.602328636179648,
      "gap_bits": 1.397671363820352,
      "per_species": {
        "phono": 2.3316208786786192,
        "lex": 2.248201932662962,
        "syntax": 2.847368793029126,
        "sem": 2.982122940347885
      }
    },
    {
      "alpha": 5.0,
      "beta": 1.0,
      "gamma": 5.0,
      "mean_entropy_bits": 2.605314106087364,
      "gap_bits": 1.3946858939126359,
      "per_species": {
        "phono": 2.3338281178033515,
        "lex": 2.2501704765566024,
        "syntax": 2.850270193572598,
        "sem": 2.986987636416904
      }
    }
  ],
  "best": {
    "alpha": 5.0,
    "beta": 1.0,
    "gamma": 0.0,
    "mean_entropy_bits": 2.601568164159256,
    "gap_bits": 1.3984318358407442,
    "per_species": {
      "phono": 2.3310650175471666,
      "lex": 2.247708431345014,
      "syntax": 2.846596204154217,
      "sem": 2.980903003590626
    }
  }
}